LICENSE
MANIFEST.in
README.rst
setup.py
django_isegory.egg-info/PKG-INFO
django_isegory.egg-info/SOURCES.txt
django_isegory.egg-info/dependency_links.txt
django_isegory.egg-info/top_level.txt
isegory/__init__.py
isegory/admin.py
isegory/models.py
isegory/tests.py
isegory/urls.py
isegory/views.py
isegory/static/isegory/css/style.css
isegory/static/isegory/img/88x31.png
isegory/static/isegory/img/core-structure.png
isegory/static/isegory/img/forkme_right_red_aa0000.png
isegory/static/isegory/img/grafico-3.png
isegory/static/isegory/img/grafico-4.png
isegory/static/isegory/img/logo.jpg
isegory/templates/isegory/base.html
isegory/templates/isegory/data_detail.html
isegory/templates/isegory/data_list.html
isegory/templates/isegory/documentation.html
isegory/templates/isegory/index.html
isegory/templates/isegory/navigation.html
isegory/templates/isegory/power_detail.html
isegory/templates/isegory/power_list.html
isegory/templates/isegory/triad_list.html