Metadata-Version: 1.1
Name: django-isegory
Version: 0.1
Summary: A simple Django app to declare the provenance of a dataset.
Home-page: http://github.com/jdelacueva/django-isegory/
Author: Javier de la Cueva
Author-email: jdelacueva@derecho-internet.org
License: AGPL
Platform: UNKNOWN
Classifier: Environment :: Web Environment
Classifier: Framework :: Django
Classifier: Intended Audience :: Developers
Classifier: Operating System :: OS Independent
Classifier: Programming Language :: Python
Classifier: Programming Language :: Python :: 2.6
Classifier: Programming Language :: Python :: 2.7
Classifier: Topic :: Internet :: WWW/HTTP
Classifier: Topic :: Internet :: WWW/HTTP :: Dynamic Content
